MANIFEST.in
README.rst
setup.cfg
setup.py
django_templateloaderwithpriorities.egg-info/PKG-INFO
django_templateloaderwithpriorities.egg-info/SOURCES.txt
django_templateloaderwithpriorities.egg-info/dependency_links.txt
django_templateloaderwithpriorities.egg-info/entry_points.txt
django_templateloaderwithpriorities.egg-info/not-zip-safe
django_templateloaderwithpriorities.egg-info/requires.txt
django_templateloaderwithpriorities.egg-info/top_level.txt
templateloaderwithpriorities/__init__.py
templateloaderwithpriorities/loader.py