Metadata-Version: 1.0
Name: django-templateloaderwithpriorities
Version: 1.0dev
Summary: A Django Template Loader with priorities
Home-page: https://github.com/qubird/django-templateloaderwithpriorities
Author: Vincenzo E. Antignano (@qubird)
Author-email: @qubird
License: GNU General Public License (GPL)
Keywords: django template loader
Platform: UNKNOWN
Classifier: Programming Language :: Python
Classifier: Framework :: Django
Classifier: Intended Audience :: Developers
Classifier: License :: OSI Approved :: GNU General Public License (GPL)
